request_data.py
sogou.py
sogou-2.7.dist-info/METADATA
sogou-2.7.dist-info/WHEEL
sogou-2.7.dist-info/entry_points.txt
sogou-2.7.dist-info/top_level.txt
sogou-2.7.dist-info/RECORD
