Metadata-Version: 2.1
Name: sogou
Version: 2.7
Summary: The cli of Sogou translation
Home-page: https://github.com/weaming/sogou
Author: weaming
Author-email: garden.yuen@gmail.com
License: UNKNOWN
Project-URL: Source, https://github.com/weaming/sogou
Project-URL: Bug Reports, https://github.com/weaming/sogou
Keywords: math
Platform: UNKNOWN
Requires-Dist: requests (>=2.20.1)
Requires-Dist: simple-colors
Requires-Dist: objectify-json
Requires-Dist: jsonkv
Requires-Dist: js2py
